lazyreader.py
lazyreader-1.0.1.dist-info/DESCRIPTION.rst
lazyreader-1.0.1.dist-info/METADATA
lazyreader-1.0.1.dist-info/RECORD
lazyreader-1.0.1.dist-info/WHEEL
lazyreader-1.0.1.dist-info/metadata.json
lazyreader-1.0.1.dist-info/top_level.txt
