Metadata-Version: 2.0
Name: lazyreader
Version: 1.0.1
Summary: Lazy reading of file objects for efficient batch processing
Home-page: https://github.com/alexwlchan/lazyreader
Author: Alex Chan
Author-email: alex@alexwlchan.net
License: MIT
Platform: UNKNOWN
Classifier: Development Status :: 5 - Production/Stable
Classifier: Intended Audience :: Developers
Classifier: License :: OSI Approved :: MIT License
Classifier: Programming Language :: Python
Classifier: Programming Language :: Python :: 2.7
Classifier: Programming Language :: Python :: 3
Classifier: Programming Language :: Python :: 3.4
Classifier: Programming Language :: Python :: 3.5
Classifier: Programming Language :: Python :: 3.6
Classifier: Programming Language :: Python :: Implementation :: CPython
